{"abstracts-retrieval-response": {"item": {"ait:process-info": {"ait:status": {"@state": "update", "@type": "core", "@stage": "S300"}, "ait:date-delivered": {"@day": "06", "@year": "2020", "@timestamp": "2020-01-06T04:24:58.000058-05:00", "@month": "01"}, "ait:date-sort": {"@day": "02", "@year": "2016", "@month": "06"}}, "bibrecord": {"head": {"author-group": [{"affiliation": {"country": "Thailand", "@afid": "60028190", "@country": "tha", "city": "Bangkok", "organization": [{"$": "Department of Pathology"}, {"$": "Faculty of Medicine"}, {"$": "Chulalongkorn University"}], "affiliation-id": {"@afid": "60028190", "@dptid": "100287552"}, "@dptid": "100287552"}, "author": [{"ce:given-name": "Shanop", "preferred-name": {"ce:given-name": "Shanop", "ce:initials": "S.", "ce:surname": "Shuangshoti", "ce:indexed-name": "Shuangshoti S."}, "@seq": "1", "ce:initials": "S.", "@_fa": "true", "@type": "auth", "ce:surname": "Shuangshoti", "@auid": "55063064300", "ce:indexed-name": "Shuangshoti S."}, {"ce:given-name": "Paul Scott", "preferred-name": {"ce:given-name": "Paul Scott", "ce:initials": "P.S.", "ce:surname": "Thorner", "ce:indexed-name": "Thorner P."}, "@seq": "2", "ce:initials": "P.S.", "@_fa": "true", "@type": "auth", "ce:surname": "Thorner", "@auid": "7005811935", "ce:indexed-name": "Thorner P.S."}]}, {"affiliation": {"country": "Thailand", "@afid": "60028190", "@country": "tha", "city": "Bangkok", "organization": [{"$": "Chulalongkorn GenePRO Center"}, {"$": "Research Affairs"}, {"$": "Faculty of Medicine"}, {"$": "Chulalongkorn University"}], "affiliation-id": {"@afid": "60028190", "@dptid": "104425653"}, "@dptid": "104425653"}, "author": [{"ce:given-name": "Shanop", "preferred-name": {"ce:given-name": "Shanop", "ce:initials": "S.", "ce:surname": "Shuangshoti", "ce:indexed-name": "Shuangshoti S."}, "@seq": "1", "ce:initials": "S.", "@_fa": "true", "@type": "auth", "ce:surname": "Shuangshoti", "@auid": "55063064300", "ce:indexed-name": "Shuangshoti S."}, {"ce:given-name": "Chinachote", "preferred-name": {"ce:given-name": "Chinachote", "ce:initials": "C.", "ce:surname": "Teerapakpinyo", "ce:indexed-name": "Teerapakpinyo C."}, "@seq": "3", "ce:initials": "C.", "@_fa": "true", "@type": "auth", "ce:surname": "Teerapakpinyo", "@auid": "56653456600", "ce:indexed-name": "Teerapakpinyo C."}]}, {"affiliation": {"country": "Thailand", "@afid": "60091571", "@country": "tha", "city": "Bangkok", "organization": {"$": "WHO Collaborating Center for Research and Training on Viral Zoonoses"}, "affiliation-id": {"@afid": "60091571"}}, "author": [{"ce:given-name": "Shanop", "preferred-name": {"ce:given-name": "Shanop", "ce:initials": "S.", "ce:surname": "Shuangshoti", "ce:indexed-name": "Shuangshoti S."}, "@seq": "1", "ce:initials": "S.", "@_fa": "true", "@type": "auth", "ce:surname": "Shuangshoti", "@auid": "55063064300", "ce:indexed-name": "Shuangshoti S."}, {"ce:given-name": "Thiravat", "preferred-name": {"ce:given-name": "Thiravat", "ce:initials": "T.", "ce:surname": "Hemachudha", "ce:indexed-name": "Hemachudha T."}, "@seq": "9", "ce:initials": "T.", "@_fa": "true", "@type": "auth", "ce:surname": "Hemachudha", "@auid": "7007163205", "ce:indexed-name": "Hemachudha T."}]}, {"affiliation": {"country": "Canada", "@afid": "60030319", "@country": "can", "city": "Toronto", "organization": [{"$": "Department of Laboratory Medicine"}, {"$": "Hospital for Sick Children and University of Toronto"}], "affiliation-id": [{"@afid": "60030319", "@dptid": "113714837"}, {"@afid": "60016849"}], "@dptid": "113714837"}, "author": [{"ce:given-name": "Paul Scott", "preferred-name": {"ce:given-name": "Paul Scott", "ce:initials": "P.S.", "ce:surname": "Thorner", "ce:indexed-name": "Thorner P."}, "@seq": "2", "ce:initials": "P.S.", "@_fa": "true", "@type": "auth", "ce:surname": "Thorner", "@auid": "7005811935", "ce:indexed-name": "Thorner P.S."}]}, {"affiliation": {"country": "Thailand", "@afid": "60028190", "@country": "tha", "city": "Bangkok", "organization": [{"$": "Department of Clinical Pathology"}, {"$": "Faculty of Medicine"}, {"$": "Chulalongkorn University"}], "affiliation-id": {"@afid": "60028190", "@dptid": "104425758"}, "@dptid": "104425758"}, "author": [{"ce:given-name": "Nisachol", "preferred-name": {"ce:given-name": "Nisachol", "ce:initials": "N.", "ce:surname": "Thepa", "ce:indexed-name": "Thepa N."}, "@seq": "4", "ce:initials": "N.", "@_fa": "true", "@type": "auth", "ce:surname": "Thepa", "@auid": "55585824200", "ce:indexed-name": "Thepa N."}]}, {"affiliation": {"country": "Thailand", "@afid": "60006314", "@country": "tha", "organization": [{"$": "Department of Electrical Engineering"}, {"$": "Faculty of Engineering"}, {"$": "Prince of Songkla University"}], "affiliation-id": {"@afid": "60006314", "@dptid": "103359883"}, "@dptid": "103359883"}, "author": [{"ce:given-name": "Pornchai", "preferred-name": {"ce:given-name": "Pornchai", "ce:initials": "P.", "ce:surname": "Phukpattaranont", "ce:indexed-name": "Phukpattaranont P."}, "@seq": "5", "ce:initials": "P.", "@_fa": "true", "@type": "auth", "ce:surname": "Phukpattaranont", "@auid": "6602493030", "ce:indexed-name": "Phukpattaranont P."}]}, {"affiliation": {"country": "Thailand", "@afid": "60025527", "@country": "tha", "city": "Songkhla", "organization": [{"$": "Epidemiology Unit"}, {"$": "Faculty of Medicine"}, {"$": "Prince of Songkla University"}, {"$": "Hat Yai"}], "affiliation-id": [{"@afid": "60025527", "@dptid": "104293198"}, {"@afid": "60006314"}], "@dptid": "104293198"}, "author": [{"ce:given-name": "Nirun", "preferred-name": {"ce:given-name": "Nirun", "ce:initials": "N.", "ce:surname": "Intarut", "ce:indexed-name": "Intarut N."}, "@seq": "6", "ce:initials": "N.", "@_fa": "true", "@type": "auth", "ce:surname": "Intarut", "@auid": "23088887500", "ce:indexed-name": "Intarut N."}]}, {"affiliation": {"country": "Thailand", "@afid": "60005262", "@country": "tha", "city": "Bangkok", "organization": {"$": "Queen Saovabha Memorial Institute"}, "affiliation-id": {"@afid": "60005262"}}, "author": [{"ce:given-name": "Boonlert", "preferred-name": {"ce:given-name": "Boonlert", "ce:initials": "B.", "ce:surname": "Lumlertdacha", "ce:indexed-name": "Lumlertdacha B."}, "@seq": "7", "ce:initials": "B.", "@_fa": "true", "@type": "auth", "ce:surname": "Lumlertdacha", "@auid": "8874604400", "ce:indexed-name": "Lumlertdacha B."}, {"ce:given-name": "Veera", "preferred-name": {"ce:given-name": "Veera", "ce:initials": "V.", "ce:surname": "Tepsumethanon", "ce:indexed-name": "Tepsumethanon V."}, "@seq": "8", "ce:initials": "V.", "@_fa": "true", "@type": "auth", "ce:surname": "Tepsumethanon", "@auid": "6602544202", "ce:indexed-name": "Tepsumethanon V."}]}, {"affiliation": {"country": "Thailand", "@afid": "60028190", "@country": "tha", "city": "Bangkok", "organization": [{"$": "Department of Medicine"}, {"$": "Faculty of Medicine"}, {"$": "Chulalongkorn University"}], "affiliation-id": {"@afid": "60028190", "@dptid": "113019942"}, "@dptid": "113019942"}, "author": [{"ce:given-name": "Thiravat", "preferred-name": {"ce:given-name": "Thiravat", "ce:initials": "T.", "ce:surname": "Hemachudha", "ce:indexed-name": "Hemachudha T."}, "@seq": "9", "ce:initials": "T.", "@_fa": "true", "@type": "auth", "ce:surname": "Hemachudha", "@auid": "7007163205", "ce:indexed-name": "Hemachudha T."}]}], "citation-title": "Intracellular Spread of Rabies Virus Is Reduced in the Paralytic Form of Canine Rabies Compared to the Furious Form", "abstracts": "\u00a9 2016 Shuangshoti et al.Studies of the furious and paralytic forms of canine rabies at the early stage of disease have shown a more rapid viral colonization of the cerebral hemispheres in the furious form, as measured by viral antigen within neuronal cell bodies and viral RNA levels. Measurement of cellular processes separate from neuronal cell body provides a visual record of the spread of rabies virus which occurs across synapses. In this study, the amount of rabies viral antigen within cell processes was quantitatively assessed by image analysis in a cohort of naturally rabies infected non-vaccinated dogs (5 furious and 5 paralytic) that were sacrificed shortly after developing illness. Measurements were taken at different levels of the spinal cord, brain stem, and cerebrum. Results were compared to the amount of rabies viral antigen in neuronal cell bodies. Generally, the amount of rabies viral antigen in cell processes decreased in a rostral direction, following the pattern for the amount of rabies viral antigen in neuronal cell bodies and the percentage of involved cell bodies. However, there was a delay in cell process involvement following cell body involvement, consistent with replication occurring in the cell body region and subsequent transport out to cell processes. Greater amounts of antigen were seen in cell processes in dogs with the furious compared to paralytic form, at all anatomic levels examined. This difference was even evident when comparing (1) neurons with similar amounts of antigen, (2) similar percentages of involved neurons, and (3) anatomic levels that showed 100% positive neurons. These findings suggest that intracellular transport of the virus may be slower in the paralytic form, resulting in slower viral propagation. Possible mechanisms might involve host-specific differences in intracellular virus transport. The latter could be cytokine-mediated, since previous studies have documented greater inflammation in the paralytic form.", "correspondence": {"affiliation": {"country": "Thailand", "@country": "tha", "city": "Bangkok", "organization": [{"$": "Department of Pathology"}, {"$": "Faculty of Medicine"}, {"$": "Chulalongkorn University"}]}, "person": {"ce:given-name": "Shanop", "ce:initials": "S.", "ce:surname": "Shuangshoti", "ce:indexed-name": "Shuangshoti S."}}, "citation-info": {"citation-type": {"@code": "ar"}, "citation-language": {"@language": "English", "@xml:lang": "eng"}, "abstract-language": {"@language": "English", "@xml:lang": "eng"}}, "source": {"website": {"ce:e-address": {"$": "http://www.plosntds.org/index.php", "@type": "email"}}, "translated-sourcetitle": {"$": "PLoS Neglected Tropical Diseases", "@xml:lang": "eng"}, "volisspag": {"voliss": {"@volume": "10", "@issue": "6"}}, "@type": "j", "sourcetitle": "PLoS Neglected Tropical Diseases", "publicationdate": {"month": "06", "year": "2016", "date-text": {"@xfab-added": "true", "$": "2 June 2016"}, "day": "02"}, "sourcetitle-abbrev": "PLoS. Negl. Trop. Dis.", "@country": "usa", "issn": [{"$": "19352735", "@type": "electronic"}, {"$": "19352727", "@type": "print"}], "publicationyear": {"@first": "2016"}, "publisher": {"publishername": "Public Library of Science", "ce:e-address": {"$": "plos@plos.org", "@type": "email"}}, "article-number": "e0004748", "@srcid": "11900154404"}, "enhancement": {"classificationgroup": {"classifications": [{"@type": "EMCLASS", "classification": [{"classification-code": "17", "classification-description": "Public Health, Social Medicine and Epidemiology"}, {"classification-code": "29", "classification-description": "Clinical and Experimental Biochemistry"}, {"classification-code": "4", "classification-description": "Microbiology: Bacteriology, Mycology, Parasitology and Virology"}]}, {"@type": "ASJC", "classification": [{"$": "2739"}, {"$": "2725"}]}, {"@type": "SUBJABBR", "classification": "MEDI"}]}, "chemicalgroup": {"chemicals": {"@source": "nlm", "chemical": {"chemical-name": "Antigens, Viral"}}}}}, "item-info": {"copyright": {"$": "Copyright 2017 Elsevier B.V., All rights reserved.", "@type": "Elsevier"}, "dbcollection": [{"$": "EMBASE"}, {"$": "REAXYSCAR"}, {"$": "RMC"}, {"$": "SCOPUS"}, {"$": "Scopusbase"}, {"$": "MEDL"}], "history": {"date-created": {"@day": "27", "@year": "2017", "@timestamp": "BST 10:05:46", "@month": "03"}}, "itemidlist": {"itemid": [{"$": "611099199", "@idtype": "PUI"}, {"$": "652242756", "@idtype": "CAR-ID"}, {"$": "20160519252", "@idtype": "EMBASE"}, {"$": "20161550216", "@idtype": "REAXYSCAR"}, {"$": "2016209215", "@idtype": "RMC"}, {"$": "84978035412", "@idtype": "SCP"}, {"$": "84978035412", "@idtype": "SGR"}, {"$": "615084916", "@idtype": "PUIsecondary"}, {"$": "27253394", "@idtype": "MEDL"}], "ce:doi": "10.1371/journal.pntd.0004748"}}, "tail": {"bibliography": {"@refcount": "22", "reference": [{"ref-fulltext": "Rupprecht CE, Hanlon CA, Hemachudha T, Rabies: re-examined. Lancet Infect Dis. 2002; 2: 327\u2013343. 12144896", "@id": "1", "ref-info": {"ref-publicationyear": {"@first": "2002"}, "ref-title": {"ref-titletext": "Rabies: re-examined"}, "refd-itemidlist": {"itemid": {"$": "0036276613", "@idtype": "SGR"}}, "ref-volisspag": {"voliss": {"@volume": "2"}, "pagerange": {"@first": "327", "@last": "343"}}, "ref-text": "12144896, .;:\u2013", "ref-authors": {"author": [{"@seq": "1", "ce:initials": "C.E.", "@_fa": "true", "ce:surname": "Rupprecht", "ce:indexed-name": "Rupprecht C.E."}, {"@seq": "2", "ce:initials": "C.A.", "@_fa": "true", "ce:surname": "Hanlon", "ce:indexed-name": "Hanlon C.A."}, {"@seq": "3", "ce:initials": "T.", "@_fa": "true", "ce:surname": "Hemachudha", "ce:indexed-name": "Hemachudha T."}]}, "ref-sourcetitle": "Lancet Infect Dis"}}, {"ref-fulltext": "Shuangshoti S, Thepa N, Phukpattaranont P, Jittmittraphap A, Intarut N, Tepsumethanon V, et al. Reduced viral burden in paralytic compared to furious canine rabies is associated with prominent inflammation at the brainstem level. BMC Vet Res. 2013; 9: 31. doi: 10.1186/1746-6148-9-3123410236", "@id": "2", "ref-info": {"ref-publicationyear": {"@first": "2013"}, "ref-website": {"ce:e-address": {"$": "10.1186/1746-6148-9-31", "@type": "email"}}, "ref-title": {"ref-titletext": "Reduced viral burden in paralytic compared to furious canine rabies is associated with prominent inflammation at the brainstem level"}, "refd-itemidlist": {"itemid": {"$": "84873597712", "@idtype": "SGR"}}, "ref-volisspag": {"voliss": {"@volume": "9"}, "pagerange": {"@first": "31"}}, "ref-text": "23410236, ..;:", "ref-authors": {"author": [{"@seq": "1", "ce:initials": "S.", "@_fa": "true", "ce:surname": "Shuangshoti", "ce:indexed-name": "Shuangshoti S."}, {"@seq": "2", "ce:initials": "N.", "@_fa": "true", "ce:surname": "Thepa", "ce:indexed-name": "Thepa N."}, {"@seq": "3", "ce:initials": "P.", "@_fa": "true", "ce:surname": "Phukpattaranont", "ce:indexed-name": "Phukpattaranont P."}, {"@seq": "4", "ce:initials": "A.", "@_fa": "true", "ce:surname": "Jittmittraphap", "ce:indexed-name": "Jittmittraphap A."}, {"@seq": "5", "ce:initials": "N.", "@_fa": "true", "ce:surname": "Intarut", "ce:indexed-name": "Intarut N."}, {"@seq": "6", "ce:initials": "V.", "@_fa": "true", "ce:surname": "Tepsumethanon", "ce:indexed-name": "Tepsumethanon V."}], "et-al": null}, "ref-sourcetitle": "BMC Vet Res"}}, {"ref-fulltext": "Hemachudha T, Ugolini G, Wacharapluesadee S, Sungkarat W, Shuangshoti S, Laothamatas J, Human rabies: neuropathogenesis, diagnosis, and management. Lancet Neurol. 2013; 12: 498\u2013513. doi: 10.1016/S1474-4422(13)70038-323602163", "@id": "3", "ref-info": {"ref-publicationyear": {"@first": "2013"}, "ref-website": {"ce:e-address": {"$": "10.1016/S1474-4422(13)70038-3", "@type": "email"}}, "ref-title": {"ref-titletext": "Human rabies: neuropathogenesis, diagnosis, and management"}, "refd-itemidlist": {"itemid": {"$": "84876461706", "@idtype": "SGR"}}, "ref-volisspag": {"voliss": {"@volume": "12"}, "pagerange": {"@first": "498", "@last": "513"}}, "ref-text": "23602163, .;:\u2013", "ref-authors": {"author": [{"@seq": "1", "ce:initials": "T.", "@_fa": "true", "ce:surname": "Hemachudha", "ce:indexed-name": "Hemachudha T."}, {"@seq": "2", "ce:initials": "G.", "@_fa": "true", "ce:surname": "Ugolini", "ce:indexed-name": "Ugolini G."}, {"@seq": "3", "ce:initials": "S.", "@_fa": "true", "ce:surname": "Wacharapluesadee", "ce:indexed-name": "Wacharapluesadee S."}, {"@seq": "4", "ce:initials": "W.", "@_fa": "true", "ce:surname": "Sungkarat", "ce:indexed-name": "Sungkarat W."}, {"@seq": "5", "ce:initials": "S.", "@_fa": "true", "ce:surname": "Shuangshoti", "ce:indexed-name": "Shuangshoti S."}, {"@seq": "6", "ce:initials": "J.", "@_fa": "true", "ce:surname": "Laothamatas", "ce:indexed-name": "Laothamatas J."}]}, "ref-sourcetitle": "Lancet Neurol"}}, {"ref-fulltext": "Mitrabhakdi E, Shuangshoti S, Wannakrairot P, Lewis RA, Susuki K, Laothamatas J, et al. Difference in neuropathogenetic mechanisms in human furious and paralytic rabies. J Neurol Sci. 2005; 238: 3\u201310. 16226769", "@id": "4", "ref-info": {"ref-publicationyear": {"@first": "2005"}, "ref-title": {"ref-titletext": "Difference in neuropathogenetic mechanisms in human furious and paralytic rabies"}, "refd-itemidlist": {"itemid": {"$": "27644484946", "@idtype": "SGR"}}, "ref-volisspag": {"voliss": {"@volume": "238"}, "pagerange": {"@first": "3", "@last": "10"}}, "ref-text": "16226769, ..;:\u2013", "ref-authors": {"author": [{"@seq": "1", "ce:initials": "E.", "@_fa": "true", "ce:surname": "Mitrabhakdi", "ce:indexed-name": "Mitrabhakdi E."}, {"@seq": "2", "ce:initials": "S.", "@_fa": "true", "ce:surname": "Shuangshoti", "ce:indexed-name": "Shuangshoti S."}, {"@seq": "3", "ce:initials": "P.", "@_fa": "true", "ce:surname": "Wannakrairot", "ce:indexed-name": "Wannakrairot P."}, {"@seq": "4", "ce:initials": "R.A.", "@_fa": "true", "ce:surname": "Lewis", "ce:indexed-name": "Lewis R.A."}, {"@seq": "5", "ce:initials": "K.", "@_fa": "true", "ce:surname": "Susuki", "ce:indexed-name": "Susuki K."}, {"@seq": "6", "ce:initials": "J.", "@_fa": "true", "ce:surname": "Laothamatas", "ce:indexed-name": "Laothamatas J."}], "et-al": null}, "ref-sourcetitle": "J Neurol Sci"}}, {"ref-fulltext": "Tirawatnpong S, Hemachudha T, Manutsathit S, Shuangshoti S, Phanthumchinda K, Phanuphak P, Regional distribution of rabies viral antigen in central nervous system of human encephalitic and paralytic rabies. J Neurol Sci. 1989; 92: 91\u20139. 2769305", "@id": "5", "ref-info": {"ref-publicationyear": {"@first": "1989"}, "ref-title": {"ref-titletext": "Regional distribution of rabies viral antigen in central nervous system of human encephalitic and paralytic rabies"}, "refd-itemidlist": {"itemid": {"$": "0024448286", "@idtype": "SGR"}}, "ref-volisspag": {"voliss": {"@volume": "92"}, "pagerange": {"@first": "91", "@last": "99"}}, "ref-text": "2769305, .;:\u2013", "ref-authors": {"author": [{"@seq": "1", "ce:initials": "S.", "@_fa": "true", "ce:surname": "Tirawatnpong", "ce:indexed-name": "Tirawatnpong S."}, {"@seq": "2", "ce:initials": "T.", "@_fa": "true", "ce:surname": "Hemachudha", "ce:indexed-name": "Hemachudha T."}, {"@seq": "3", "ce:initials": "S.", "@_fa": "true", "ce:surname": "Manutsathit", "ce:indexed-name": "Manutsathit S."}, {"@seq": "4", "ce:initials": "S.", "@_fa": "true", "ce:surname": "Shuangshoti", "ce:indexed-name": "Shuangshoti S."}, {"@seq": "5", "ce:initials": "K.", "@_fa": "true", "ce:surname": "Phanthumchinda", "ce:indexed-name": "Phanthumchinda K."}, {"@seq": "6", "ce:initials": "P.", "@_fa": "true", "ce:surname": "Phanuphak", "ce:indexed-name": "Phanuphak P."}]}, "ref-sourcetitle": "J Neurol Sci"}}, {"ref-fulltext": "Laothamatas J, Wacharapluesadee S, Lumlertdacha B, Ampawong S, Tepsumethanon V, Shuangshoti S, et al. Furious and paralytic rabies of canine origin: neuroimaging with virological and cytokine studies. J Neurovirol. 2008; 14: 119\u201329. doi: 10.1080/1355028070188385718444083", "@id": "6", "ref-info": {"ref-publicationyear": {"@first": "2008"}, "ref-website": {"ce:e-address": {"$": "10.1080/13550280701883857", "@type": "email"}}, "ref-title": {"ref-titletext": "Furious and paralytic rabies of canine origin: neuroimaging with virological and cytokine studies"}, "refd-itemidlist": {"itemid": {"$": "42949098391", "@idtype": "SGR"}}, "ref-volisspag": {"voliss": {"@volume": "14"}, "pagerange": {"@first": "119", "@last": "129"}}, "ref-text": "18444083, ..;:\u2013", "ref-authors": {"author": [{"@seq": "1", "ce:initials": "J.", "@_fa": "true", "ce:surname": "Laothamatas", "ce:indexed-name": "Laothamatas J."}, {"@seq": "2", "ce:initials": "S.", "@_fa": "true", "ce:surname": "Wacharapluesadee", "ce:indexed-name": "Wacharapluesadee S."}, {"@seq": "3", "ce:initials": "B.", "@_fa": "true", "ce:surname": "Lumlertdacha", "ce:indexed-name": "Lumlertdacha B."}, {"@seq": "4", "ce:initials": "S.", "@_fa": "true", "ce:surname": "Ampawong", "ce:indexed-name": "Ampawong S."}, {"@seq": "5", "ce:initials": "V.", "@_fa": "true", "ce:surname": "Tepsumethanon", "ce:indexed-name": "Tepsumethanon V."}, {"@seq": "6", "ce:initials": "S.", "@_fa": "true", "ce:surname": "Shuangshoti", "ce:indexed-name": "Shuangshoti S."}], "et-al": null}, "ref-sourcetitle": "J Neurovirol"}}, {"ref-fulltext": "Dumrongphol H, Srikiatkhachorn A, Hemachudha T, Kotchabhakdi N, Govitrapong P, Alteration of muscarinic acetylcholine receptors in rabies viral-infected dog brains. J Neurol Sci. 1996; 137: 1\u20136. 9120481", "@id": "7", "ref-info": {"ref-publicationyear": {"@first": "1996"}, "ref-title": {"ref-titletext": "Alteration of muscarinic acetylcholine receptors in rabies viral-infected dog brains"}, "refd-itemidlist": {"itemid": {"$": "0029880158", "@idtype": "SGR"}}, "ref-volisspag": {"voliss": {"@volume": "137"}, "pagerange": {"@first": "1", "@last": "6"}}, "ref-text": "9120481, .;:\u2013", "ref-authors": {"author": [{"@seq": "1", "ce:initials": "H.", "@_fa": "true", "ce:surname": "Dumrongphol", "ce:indexed-name": "Dumrongphol H."}, {"@seq": "2", "ce:initials": "A.", "@_fa": "true", "ce:surname": "Srikiatkhachorn", "ce:indexed-name": "Srikiatkhachorn A."}, {"@seq": "3", "ce:initials": "T.", "@_fa": "true", "ce:surname": "Hemachudha", "ce:indexed-name": "Hemachudha T."}, {"@seq": "4", "ce:initials": "N.", "@_fa": "true", "ce:surname": "Kotchabhakdi", "ce:indexed-name": "Kotchabhakdi N."}, {"@seq": "5", "ce:initials": "P.", "@_fa": "true", "ce:surname": "Govitrapong", "ce:indexed-name": "Govitrapong P."}]}, "ref-sourcetitle": "J Neurol Sci"}}, {"ref-fulltext": "Laothamatas J, Sungkarat W, Hemachudha T, Neuroimaging in rabies. Adv Virus Res. 2011; 79: 309\u2013327. doi: 10.1016/B978-0-12-387040-7.00014-721601052", "@id": "8", "ref-info": {"ref-publicationyear": {"@first": "2011"}, "ref-website": {"ce:e-address": {"$": "10.1016/B978-0-12-387040-7.00014-7", "@type": "email"}}, "ref-title": {"ref-titletext": "Neuroimaging in rabies"}, "refd-itemidlist": {"itemid": {"$": "79956068203", "@idtype": "SGR"}}, "ref-volisspag": {"voliss": {"@volume": "79"}, "pagerange": {"@first": "309", "@last": "327"}}, "ref-text": "21601052, .;:\u2013", "ref-authors": {"author": [{"@seq": "1", "ce:initials": "J.", "@_fa": "true", "ce:surname": "Laothamatas", "ce:indexed-name": "Laothamatas J."}, {"@seq": "2", "ce:initials": "W.", "@_fa": "true", "ce:surname": "Sungkarat", "ce:indexed-name": "Sungkarat W."}, {"@seq": "3", "ce:initials": "T.", "@_fa": "true", "ce:surname": "Hemachudha", "ce:indexed-name": "Hemachudha T."}]}, "ref-sourcetitle": "Adv Virus Res"}}, {"ref-fulltext": "Laothamatas J, Sungkarat W, Hemachudha T, Rupprecht CE, Thirumeni N, Rabies diagnosis: MR imaging. In: Current laboratory techniques in rabies diagnosis, research, and prevention, Vol 1. Tokyo: Academic Press; 2014. pp. 221\u2013231.", "@id": "9", "ref-info": {"ref-publicationyear": {"@first": "2014"}, "refd-itemidlist": {"itemid": {"$": "84941764602", "@idtype": "SGR"}}, "ref-volisspag": {"voliss": {"@volume": "Vol 1"}, "pagerange": {"@first": "221", "@last": "231"}}, "ref-text": ". In:,.:;. pp.\u2013", "ref-authors": {"author": [{"@seq": "1", "ce:initials": "J.", "@_fa": "true", "ce:surname": "Laothamatas", "ce:indexed-name": "Laothamatas J."}, {"@seq": "2", "ce:initials": "W.", "@_fa": "true", "ce:surname": "Sungkarat", "ce:indexed-name": "Sungkarat W."}, {"@seq": "3", "ce:initials": "T.", "@_fa": "true", "ce:surname": "Hemachudha", "ce:indexed-name": "Hemachudha T."}, {"@seq": "4", "ce:initials": "C.E.", "@_fa": "true", "ce:surname": "Rupprecht", "ce:indexed-name": "Rupprecht C.E."}, {"@seq": "5", "ce:initials": "N.", "@_fa": "true", "ce:surname": "Thirumeni", "ce:indexed-name": "Thirumeni N."}]}, "ref-sourcetitle": "Current laboratory techniques in rabies diagnosis, research, and prevention"}}, {"ref-fulltext": "Stein LT, Rech RR, Harrison L, Brown CC, Immunohistochemical study of rabies virus within the central nervous system of domestic and wildlife species. Vet Pathol. 2010; 47: 630\u2013633. doi: 10.1177/030098581037001320484176", "@id": "10", "ref-info": {"ref-publicationyear": {"@first": "2010"}, "ref-website": {"ce:e-address": {"$": "10.1177/0300985810370013", "@type": "email"}}, "ref-title": {"ref-titletext": "Immunohistochemical study of rabies virus within the central nervous system of domestic and wildlife species"}, "refd-itemidlist": {"itemid": {"$": "77954940497", "@idtype": "SGR"}}, "ref-volisspag": {"voliss": {"@volume": "47"}, "pagerange": {"@first": "630", "@last": "633"}}, "ref-text": "20484176, .;:\u2013", "ref-authors": {"author": [{"@seq": "1", "ce:initials": "L.T.", "@_fa": "true", "ce:surname": "Stein", "ce:indexed-name": "Stein L.T."}, {"@seq": "2", "ce:initials": "R.R.", "@_fa": "true", "ce:surname": "Rech", "ce:indexed-name": "Rech R.R."}, {"@seq": "3", "ce:initials": "L.", "@_fa": "true", "ce:surname": "Harrison", "ce:indexed-name": "Harrison L."}, {"@seq": "4", "ce:initials": "C.C.", "@_fa": "true", "ce:surname": "Brown", "ce:indexed-name": "Brown C.C."}]}, "ref-sourcetitle": "Vet Pathol"}}, {"ref-fulltext": "Fletcher TF, Canine Brain Transections 2007. Available: http://vanat.cvm.umn.edu/brainsect/index.html.", "@id": "11", "ref-info": {"ref-website": {"ce:e-address": {"$": "http://vanat.cvm.umn.edu/brainsect/index.html", "@type": "email"}}, "refd-itemidlist": {"itemid": {"$": "84978131381", "@idtype": "SGR"}}, "ref-text": "Fletcher TF, Canine Brain Transections 2007. Available:"}}, {"ref-fulltext": "Tsiang H, Ceccaldi PE, Lycke E, Rabies virus infection and transport in human sensory dorsal root ganglia neurons. J Gen Virol. 1991; 72: 1191\u20131194. 2033395", "@id": "12", "ref-info": {"ref-publicationyear": {"@first": "1991"}, "ref-title": {"ref-titletext": "Rabies virus infection and transport in human sensory dorsal root ganglia neurons"}, "refd-itemidlist": {"itemid": {"$": "0025810706", "@idtype": "SGR"}}, "ref-volisspag": {"voliss": {"@volume": "72"}, "pagerange": {"@first": "1191", "@last": "1194"}}, "ref-text": "2033395, .;:\u2013", "ref-authors": {"author": [{"@seq": "1", "ce:initials": "H.", "@_fa": "true", "ce:surname": "Tsiang", "ce:indexed-name": "Tsiang H."}, {"@seq": "2", "ce:initials": "P.E.", "@_fa": "true", "ce:surname": "Ceccaldi", "ce:indexed-name": "Ceccaldi P.E."}, {"@seq": "3", "ce:initials": "E.", "@_fa": "true", "ce:surname": "Lycke", "ce:indexed-name": "Lycke E."}]}, "ref-sourcetitle": "J Gen Virol"}}, {"ref-fulltext": "Ugolini G, Rabies virus as a transneuronal tracer of neuronal connections. Adv Vir Res. 2011; 79: 165\u2013202.", "@id": "13", "ref-info": {"ref-publicationyear": {"@first": "2011"}, "ref-title": {"ref-titletext": "Rabies virus as a transneuronal tracer of neuronal connections"}, "refd-itemidlist": {"itemid": {"$": "79956112306", "@idtype": "SGR"}}, "ref-volisspag": {"voliss": {"@volume": "79"}, "pagerange": {"@first": "165", "@last": "202"}}, "ref-text": ".;:\u2013", "ref-authors": {"author": [{"@seq": "1", "ce:initials": "G.", "@_fa": "true", "ce:surname": "Ugolini", "ce:indexed-name": "Ugolini G."}]}, "ref-sourcetitle": "Adv Vir Res"}}, {"ref-fulltext": "Gluska S, Zahavi EE, Chein M, Gradus T, Bauer A, Finke S, Perlson E, Rabies virus hijacks and accelerates the p75NTR retrograde axonal transport machinery. PLoS Pathog. 2014; 10: e1004348. doi: 10.1371/journal.ppat.100434825165859", "@id": "14", "ref-info": {"ref-publicationyear": {"@first": "2014"}, "ref-website": {"ce:e-address": {"$": "10.1371/journal.ppat.1004348", "@type": "email"}}, "ref-title": {"ref-titletext": "Rabies virus hijacks and accelerates the p75NTR retrograde axonal transport machinery"}, "refd-itemidlist": {"itemid": {"$": "84911477882", "@idtype": "SGR"}}, "ref-volisspag": {"voliss": {"@volume": "10"}, "pagerange": {"@first": "e1004348"}}, "ref-text": "25165859, .;:", "ref-authors": {"author": [{"@seq": "1", "ce:initials": "S.", "@_fa": "true", "ce:surname": "Gluska", "ce:indexed-name": "Gluska S."}, {"@seq": "2", "ce:initials": "E.E.", "@_fa": "true", "ce:surname": "Zahavi", "ce:indexed-name": "Zahavi E.E."}, {"@seq": "3", "ce:initials": "M.", "@_fa": "true", "ce:surname": "Chein", "ce:indexed-name": "Chein M."}, {"@seq": "4", "ce:initials": "T.", "@_fa": "true", "ce:surname": "Gradus", "ce:indexed-name": "Gradus T."}, {"@seq": "5", "ce:initials": "A.", "@_fa": "true", "ce:surname": "Bauer", "ce:indexed-name": "Bauer A."}, {"@seq": "6", "ce:initials": "S.", "@_fa": "true", "ce:surname": "Finke", "ce:indexed-name": "Finke S."}, {"@seq": "7", "ce:initials": "E.", "@_fa": "true", "ce:surname": "Perlson", "ce:indexed-name": "Perlson E."}]}, "ref-sourcetitle": "PLoS Pathog"}}, {"ref-fulltext": "Suja MS, Mahadevan A, Madhusudhana SN, Vijayasarathi SK, Shankar SK, Neuroanatomical mapping of rabies nucleocapsid viral antigen distribution and apoptosis in pathogenesis in street dog rabies\u2014an immunohistochemical study. Clin Neuropathol. 2009; 28: 113\u2013124. 19353843", "@id": "15", "ref-info": {"ref-publicationyear": {"@first": "2009"}, "ref-title": {"ref-titletext": "Neuroanatomical mapping of rabies nucleocapsid viral antigen distribution and apoptosis in pathogenesis in street dog rabies\u2014an immunohistochemical study"}, "refd-itemidlist": {"itemid": {"$": "65349120021", "@idtype": "SGR"}}, "ref-volisspag": {"voliss": {"@volume": "28"}, "pagerange": {"@first": "113", "@last": "124"}}, "ref-text": "19353843, .;:\u2013", "ref-authors": {"author": [{"@seq": "1", "ce:initials": "M.S.", "@_fa": "true", "ce:surname": "Suja", "ce:indexed-name": "Suja M.S."}, {"@seq": "2", "ce:initials": "A.", "@_fa": "true", "ce:surname": "Mahadevan", "ce:indexed-name": "Mahadevan A."}, {"@seq": "3", "ce:initials": "S.N.", "@_fa": "true", "ce:surname": "Madhusudhana", "ce:indexed-name": "Madhusudhana S.N."}, {"@seq": "4", "ce:initials": "S.K.", "@_fa": "true", "ce:surname": "Vijayasarathi", "ce:indexed-name": "Vijayasarathi S.K."}, {"@seq": "5", "ce:initials": "S.K.", "@_fa": "true", "ce:surname": "Shankar", "ce:indexed-name": "Shankar S.K."}]}, "ref-sourcetitle": "Clin Neuropathol"}}, {"ref-fulltext": "Bingham J, van der Merwe M, Distribution of rabies antigen in infected brain material: determining the reliability of different regions of the brain for the rabies fluorescent antibody test. J Virol Methods. 2002; 101: 85\u201394. 11849687", "@id": "16", "ref-info": {"ref-publicationyear": {"@first": "2002"}, "ref-title": {"ref-titletext": "Distribution of rabies antigen in infected brain material: determining the reliability of different regions of the brain for the rabies fluorescent antibody test"}, "refd-itemidlist": {"itemid": {"$": "0036182571", "@idtype": "SGR"}}, "ref-volisspag": {"voliss": {"@volume": "101"}, "pagerange": {"@first": "85", "@last": "94"}}, "ref-text": "11849687, .;:\u2013", "ref-authors": {"author": [{"@seq": "1", "ce:initials": "J.", "@_fa": "true", "ce:surname": "Bingham", "ce:indexed-name": "Bingham J."}, {"@seq": "2", "ce:initials": "M.", "@_fa": "true", "ce:surname": "van der Merwe", "ce:indexed-name": "van der Merwe M."}]}, "ref-sourcetitle": "J Virol Methods"}}, {"ref-fulltext": "Laothamatas J, Hemachudha T, Mitrabhakdi E, Wannakrairot P, Tulayadaechanont S, MR imaging in human rabies. Am J Neuroradiol. 2003; 24: 1102\u20131109. 12812933", "@id": "17", "ref-info": {"ref-publicationyear": {"@first": "2003"}, "ref-title": {"ref-titletext": "MR imaging in human rabies"}, "refd-itemidlist": {"itemid": {"$": "0037600575", "@idtype": "SGR"}}, "ref-volisspag": {"voliss": {"@volume": "24"}, "pagerange": {"@first": "1102", "@last": "1109"}}, "ref-text": "12812933, .;:\u2013", "ref-authors": {"author": [{"@seq": "1", "ce:initials": "J.", "@_fa": "true", "ce:surname": "Laothamatas", "ce:indexed-name": "Laothamatas J."}, {"@seq": "2", "ce:initials": "T.", "@_fa": "true", "ce:surname": "Hemachudha", "ce:indexed-name": "Hemachudha T."}, {"@seq": "3", "ce:initials": "E.", "@_fa": "true", "ce:surname": "Mitrabhakdi", "ce:indexed-name": "Mitrabhakdi E."}, {"@seq": "4", "ce:initials": "P.", "@_fa": "true", "ce:surname": "Wannakrairot", "ce:indexed-name": "Wannakrairot P."}, {"@seq": "5", "ce:initials": "S.", "@_fa": "true", "ce:surname": "Tulayadaechanont", "ce:indexed-name": "Tulayadaechanont S."}]}, "ref-sourcetitle": "Am J Neuroradiol"}}, {"ref-fulltext": "Hemachudha T, Wacharapluesadee S, Lumlertdaecha B, Orciari LA, Rupprecht CE, La-Ongpant M, et al. Sequence analysis of rabies virus in humans exhibiting encephalitic or paralytic rabies. J Infect Dis. 2003; 188:960\u2013966. 14513414", "@id": "18", "ref-info": {"ref-publicationyear": {"@first": "2003"}, "ref-title": {"ref-titletext": "Sequence analysis of rabies virus in humans exhibiting encephalitic or paralytic rabies"}, "refd-itemidlist": {"itemid": {"$": "0142010635", "@idtype": "SGR"}}, "ref-volisspag": {"voliss": {"@volume": "188"}, "pagerange": {"@first": "960", "@last": "966"}}, "ref-text": "14513414, ..;:\u2013", "ref-authors": {"author": [{"@seq": "1", "ce:initials": "T.", "@_fa": "true", "ce:surname": "Hemachudha", "ce:indexed-name": "Hemachudha T."}, {"@seq": "2", "ce:initials": "S.", "@_fa": "true", "ce:surname": "Wacharapluesadee", "ce:indexed-name": "Wacharapluesadee S."}, {"@seq": "3", "ce:initials": "B.", "@_fa": "true", "ce:surname": "Lumlertdaecha", "ce:indexed-name": "Lumlertdaecha B."}, {"@seq": "4", "ce:initials": "L.A.", "@_fa": "true", "ce:surname": "Orciari", "ce:indexed-name": "Orciari L.A."}, {"@seq": "5", "ce:initials": "C.E.", "@_fa": "true", "ce:surname": "Rupprecht", "ce:indexed-name": "Rupprecht C.E."}, {"@seq": "6", "ce:initials": "M.", "@_fa": "true", "ce:surname": "La-Ongpant", "ce:indexed-name": "La-Ongpant M."}], "et-al": null}, "ref-sourcetitle": "J Infect Dis"}}, {"ref-fulltext": "Jackson AC, Diabolical effects of rabies encephalitis. J Neurovirol. 2016; 22: 8\u201313. doi: 10.1007/s13365-015-0351-125994917", "@id": "19", "ref-info": {"ref-publicationyear": {"@first": "2016"}, "ref-website": {"ce:e-address": {"$": "10.1007/s13365-015-0351-1", "@type": "email"}}, "ref-title": {"ref-titletext": "Diabolical effects of rabies encephalitis"}, "refd-itemidlist": {"itemid": {"$": "84957844099", "@idtype": "SGR"}}, "ref-volisspag": {"voliss": {"@volume": "22"}, "pagerange": {"@first": "8", "@last": "13"}}, "ref-text": "25994917, .;:\u2013", "ref-authors": {"author": [{"@seq": "1", "ce:initials": "A.C.", "@_fa": "true", "ce:surname": "Jackson", "ce:indexed-name": "Jackson A.C."}]}, "ref-sourcetitle": "J Neurovirol"}}, {"ref-fulltext": "Li XQ, Sarmento L, Fu ZF, Degeneration of neuronal processes after infection with pathogenic, but not attenuated, rabies viruses. J Virol. 2005; 79:10063\u20131006816014967", "@id": "20", "ref-info": {"ref-publicationyear": {"@first": "2005"}, "ref-title": {"ref-titletext": "Degeneration of neuronal processes after infection with pathogenic, but not attenuated, rabies viruses"}, "refd-itemidlist": {"itemid": {"$": "22544462822", "@idtype": "SGR"}}, "ref-volisspag": {"voliss": {"@volume": "79"}, "pagerange": {"@first": "10063", "@last": "10068"}}, "ref-text": "16014967", "ref-authors": {"author": [{"@seq": "1", "ce:initials": "X.Q.", "@_fa": "true", "ce:surname": "Li", "ce:indexed-name": "Li X.Q."}, {"@seq": "2", "ce:initials": "L.", "@_fa": "true", "ce:surname": "Sarmento", "ce:indexed-name": "Sarmento L."}, {"@seq": "3", "ce:initials": "Z.F.", "@_fa": "true", "ce:surname": "Fu", "ce:indexed-name": "Fu Z.F."}]}, "ref-sourcetitle": "J Virol"}}, {"ref-fulltext": "Kammouni W, Wood H, Saleh A, Appolinario CM, Fernyhough P, Jackson AC, Rabies virus phosphoprotein interacts with mitochondrial Complex I and induces mitochondrial dysfunction and oxidative stress. J Neurovirol. 2015; 21:370\u2013382. doi: 10.1007/s13365-015-0320-825698500", "@id": "21", "ref-info": {"ref-publicationyear": {"@first": "2015"}, "ref-website": {"ce:e-address": {"$": "10.1007/s13365-015-0320-8", "@type": "email"}}, "ref-title": {"ref-titletext": "Rabies virus phosphoprotein interacts with mitochondrial Complex I and induces mitochondrial dysfunction and oxidative stress"}, "refd-itemidlist": {"itemid": {"$": "84938414375", "@idtype": "SGR"}}, "ref-volisspag": {"voliss": {"@volume": "21"}, "pagerange": {"@first": "370", "@last": "382"}}, "ref-text": "25698500, .;:\u2013", "ref-authors": {"author": [{"@seq": "1", "ce:initials": "W.", "@_fa": "true", "ce:surname": "Kammouni", "ce:indexed-name": "Kammouni W."}, {"@seq": "2", "ce:initials": "H.", "@_fa": "true", "ce:surname": "Wood", "ce:indexed-name": "Wood H."}, {"@seq": "3", "ce:initials": "A.", "@_fa": "true", "ce:surname": "Saleh", "ce:indexed-name": "Saleh A."}, {"@seq": "4", "ce:initials": "C.M.", "@_fa": "true", "ce:surname": "Appolinario", "ce:indexed-name": "Appolinario C.M."}, {"@seq": "5", "ce:initials": "P.", "@_fa": "true", "ce:surname": "Fernyhough", "ce:indexed-name": "Fernyhough P."}, {"@seq": "6", "ce:initials": "A.C.", "@_fa": "true", "ce:surname": "Jackson", "ce:indexed-name": "Jackson A.C."}]}, "ref-sourcetitle": "J Neurovirol"}}, {"ref-fulltext": "Suja MS, Mahadevan A, Madhusudana SN, Shankar SK, Role of apoptosis in rabies viral encephalitis: a comparative study in mice, canine, and human brain with a review of literature. Patholog Res Int. 2011; 2011: 374286. doi: 10.4061/2011/37428621876844", "@id": "22", "ref-info": {"ref-publicationyear": {"@first": "2011"}, "ref-website": {"ce:e-address": {"$": "10.4061/2011/374286", "@type": "email"}}, "ref-title": {"ref-titletext": "Role of apoptosis in rabies viral encephalitis: a comparative study in mice, canine, and human brain with a review of literature"}, "refd-itemidlist": {"itemid": {"$": "84868146764", "@idtype": "SGR"}}, "ref-volisspag": {"voliss": {"@volume": "2011"}, "pagerange": {"@first": "374286"}}, "ref-text": "21876844, .;:", "ref-authors": {"author": [{"@seq": "1", "ce:initials": "M.S.", "@_fa": "true", "ce:surname": "Suja", "ce:indexed-name": "Suja M.S."}, {"@seq": "2", "ce:initials": "A.", "@_fa": "true", "ce:surname": "Mahadevan", "ce:indexed-name": "Mahadevan A."}, {"@seq": "3", "ce:initials": "S.N.", "@_fa": "true", "ce:surname": "Madhusudana", "ce:indexed-name": "Madhusudana S.N."}, {"@seq": "4", "ce:initials": "S.K.", "@_fa": "true", "ce:surname": "Shankar", "ce:indexed-name": "Shankar S.K."}]}, "ref-sourcetitle": "Patholog Res Int"}}]}}}}, "affiliation": [{"affiliation-city": "Bangkok", "@id": "60028190", "affilname": "Chulalongkorn University", "@href": "https://api.elsevier.com/content/affiliation/affiliation_id/60028190", "affiliation-country": "Thailand"}, {"affiliation-city": "Nanthaburi", "@id": "60091571", "affilname": "World Health Organization, Thailand", "@href": "https://api.elsevier.com/content/affiliation/affiliation_id/60091571", "affiliation-country": "Thailand"}, {"affiliation-city": "Toronto", "@id": "60030319", "affilname": "The Hospital for Sick Children", "@href": "https://api.elsevier.com/content/affiliation/affiliation_id/60030319", "affiliation-country": "Canada"}, {"affiliation-city": "Hatyai", "@id": "60025527", "affilname": "Faculty of Medicine, Prince of Songkla University", "@href": "https://api.elsevier.com/content/affiliation/affiliation_id/60025527", "affiliation-country": "Thailand"}, {"affiliation-city": "Hatyai", "@id": "60006314", "affilname": "Prince of Songkla University", "@href": "https://api.elsevier.com/content/affiliation/affiliation_id/60006314", "affiliation-country": "Thailand"}, {"affiliation-city": "Bangkok", "@id": "60005262", "affilname": "Queen Saovabha Memorial Institute", "@href": "https://api.elsevier.com/content/affiliation/affiliation_id/60005262", "affiliation-country": "Thailand"}], "coredata": {"srctype": "j", "eid": "2-s2.0-84978035412", "dc:description": "Studies of the furious and paralytic forms of canine rabies at the early stage of disease have shown a more rapid viral colonization of the cerebral hemispheres in the furious form, as measured by viral antigen within neuronal cell bodies and viral RNA levels. Measurement of cellular processes separate from neuronal cell body provides a visual record of the spread of rabies virus which occurs across synapses. In this study, the amount of rabies viral antigen within cell processes was quantitatively assessed by image analysis in a cohort of naturally rabies infected non-vaccinated dogs (5 furious and 5 paralytic) that were sacrificed shortly after developing illness. Measurements were taken at different levels of the spinal cord, brain stem, and cerebrum. Results were compared to the amount of rabies viral antigen in neuronal cell bodies. Generally, the amount of rabies viral antigen in cell processes decreased in a rostral direction, following the pattern for the amount of rabies viral antigen in neuronal cell bodies and the percentage of involved cell bodies. However, there was a delay in cell process involvement following cell body involvement, consistent with replication occurring in the cell body region and subsequent transport out to cell processes. Greater amounts of antigen were seen in cell processes in dogs with the furious compared to paralytic form, at all anatomic levels examined. This difference was even evident when comparing (1) neurons with similar amounts of antigen, (2) similar percentages of involved neurons, and (3) anatomic levels that showed 100% positive neurons. These findings suggest that intracellular transport of the virus may be slower in the paralytic form, resulting in slower viral propagation. Possible mechanisms might involve host-specific differences in intracellular virus transport. The latter could be cytokine-mediated, since previous studies have documented greater inflammation in the paralytic form.", "pubmed-id": "27253394", "prism:coverDate": "2016-06-02", "prism:aggregationType": "Journal", "prism:url": "https://api.elsevier.com/content/abstract/scopus_id/84978035412", "dc:creator": {"author": [{"ce:given-name": "Shanop", "preferred-name": {"ce:given-name": "Shanop", "ce:initials": "S.", "ce:surname": "Shuangshoti", "ce:indexed-name": "Shuangshoti S."}, "@seq": "1", "ce:initials": "S.", "@_fa": "true", "affiliation": [{"@id": "60028190", "@href": "https://api.elsevier.com/content/affiliation/affiliation_id/60028190"}, {"@id": "60028190", "@href": "https://api.elsevier.com/content/affiliation/affiliation_id/60028190"}, {"@id": "60091571", "@href": "https://api.elsevier.com/content/affiliation/affiliation_id/60091571"}], "ce:surname": "Shuangshoti", "@auid": "55063064300", "author-url": "https://api.elsevier.com/content/author/author_id/55063064300", "ce:indexed-name": "Shuangshoti S."}]}, "link": [{"@_fa": "true", "@rel": "self", "@href": "https://api.elsevier.com/content/abstract/scopus_id/84978035412"}, {"@_fa": "true", "@rel": "scopus", "@href": "https://www.scopus.com/inward/record.uri?partnerID=HzOxMe3b&scp=84978035412&origin=inward"}, {"@_fa": "true", "@rel": "scopus-citedby", "@href": "https://www.scopus.com/inward/citedby.uri?partnerID=HzOxMe3b&scp=84978035412&origin=inward"}], "source-id": "11900154404", "citedby-count": "10", "prism:volume": "10", "subtype": "ar", "dc:title": "Intracellular Spread of Rabies Virus Is Reduced in the Paralytic Form of Canine Rabies Compared to the Furious Form", "openaccess": "1", "prism:issn": "19352735 19352727", "publishercopyright": "\u00a9 2016 Shuangshoti et al.", "article-number": "e0004748", "prism:issueIdentifier": "6", "subtypeDescription": "Article", "prism:publicationName": "PLoS Neglected Tropical Diseases", "openaccessFlag": "true", "prism:doi": "10.1371/journal.pntd.0004748", "dc:identifier": "SCOPUS_ID:84978035412", "dc:publisher": "Public Library of Scienceplos@plos.org"}, "idxterms": {"mainterm": [{"$": "Animals", "@weight": "b", "@candidate": "n"}, {"$": "Antigens, Viral", "@weight": "b", "@candidate": "n"}, {"$": "Brain", "@weight": "b", "@candidate": "n"}, {"$": "Cells, Cultured", "@weight": "b", "@candidate": "n"}, {"$": "Dog Diseases", "@weight": "b", "@candidate": "n"}, {"$": "Dogs", "@weight": "b", "@candidate": "n"}, {"$": "Neurons", "@weight": "b", "@candidate": "n"}, {"$": "Rabies", "@weight": "b", "@candidate": "n"}, {"$": "Rabies virus", "@weight": "b", "@candidate": "n"}, {"$": "Spinal Cord", "@weight": "b", "@candidate": "n"}, {"$": "Viral Load", "@weight": "b", "@candidate": "n"}]}, "language": {"@xml:lang": "eng"}, "authkeywords": null, "subject-areas": {"subject-area": [{"@_fa": "true", "$": "Public Health, Environmental and Occupational Health", "@code": "2739", "@abbrev": "MEDI"}, {"@_fa": "true", "$": "Infectious Diseases", "@code": "2725", "@abbrev": "MEDI"}]}, "authors": {"author": [{"ce:given-name": "Shanop", "preferred-name": {"ce:given-name": "Shanop", "ce:initials": "S.", "ce:surname": "Shuangshoti", "ce:indexed-name": "Shuangshoti S."}, "@seq": "1", "ce:initials": "S.", "@_fa": "true", "affiliation": [{"@id": "60028190", "@href": "https://api.elsevier.com/content/affiliation/affiliation_id/60028190"}, {"@id": "60028190", "@href": "https://api.elsevier.com/content/affiliation/affiliation_id/60028190"}, {"@id": "60091571", "@href": "https://api.elsevier.com/content/affiliation/affiliation_id/60091571"}], "ce:surname": "Shuangshoti", "@auid": "55063064300", "author-url": "https://api.elsevier.com/content/author/author_id/55063064300", "ce:indexed-name": "Shuangshoti S."}, {"ce:given-name": "Paul Scott", "preferred-name": {"ce:given-name": "Paul Scott", "ce:initials": "P.S.", "ce:surname": "Thorner", "ce:indexed-name": "Thorner P."}, "@seq": "2", "ce:initials": "P.S.", "@_fa": "true", "affiliation": [{"@id": "60028190", "@href": "https://api.elsevier.com/content/affiliation/affiliation_id/60028190"}, {"@id": "60030319", "@href": "https://api.elsevier.com/content/affiliation/affiliation_id/60030319"}], "ce:surname": "Thorner", "@auid": "7005811935", "author-url": "https://api.elsevier.com/content/author/author_id/7005811935", "ce:indexed-name": "Thorner P.S."}, {"ce:given-name": "Chinachote", "preferred-name": {"ce:given-name": "Chinachote", "ce:initials": "C.", "ce:surname": "Teerapakpinyo", "ce:indexed-name": "Teerapakpinyo C."}, "@seq": "3", "ce:initials": "C.", "@_fa": "true", "affiliation": {"@id": "60028190", "@href": "https://api.elsevier.com/content/affiliation/affiliation_id/60028190"}, "ce:surname": "Teerapakpinyo", "@auid": "56653456600", "author-url": "https://api.elsevier.com/content/author/author_id/56653456600", "ce:indexed-name": "Teerapakpinyo C."}, {"ce:given-name": "Nisachol", "preferred-name": {"ce:given-name": "Nisachol", "ce:initials": "N.", "ce:surname": "Thepa", "ce:indexed-name": "Thepa N."}, "@seq": "4", "ce:initials": "N.", "@_fa": "true", "affiliation": {"@id": "60028190", "@href": "https://api.elsevier.com/content/affiliation/affiliation_id/60028190"}, "ce:surname": "Thepa", "@auid": "55585824200", "author-url": "https://api.elsevier.com/content/author/author_id/55585824200", "ce:indexed-name": "Thepa N."}, {"ce:given-name": "Pornchai", "preferred-name": {"ce:given-name": "Pornchai", "ce:initials": "P.", "ce:surname": "Phukpattaranont", "ce:indexed-name": "Phukpattaranont P."}, "@seq": "5", "ce:initials": "P.", "@_fa": "true", "affiliation": {"@id": "60006314", "@href": "https://api.elsevier.com/content/affiliation/affiliation_id/60006314"}, "ce:surname": "Phukpattaranont", "@auid": "6602493030", "author-url": "https://api.elsevier.com/content/author/author_id/6602493030", "ce:indexed-name": "Phukpattaranont P."}, {"ce:given-name": "Nirun", "preferred-name": {"ce:given-name": "Nirun", "ce:initials": "N.", "ce:surname": "Intarut", "ce:indexed-name": "Intarut N."}, "@seq": "6", "ce:initials": "N.", "@_fa": "true", "affiliation": {"@id": "60025527", "@href": "https://api.elsevier.com/content/affiliation/affiliation_id/60025527"}, "ce:surname": "Intarut", "@auid": "23088887500", "author-url": "https://api.elsevier.com/content/author/author_id/23088887500", "ce:indexed-name": "Intarut N."}, {"ce:given-name": "Boonlert", "preferred-name": {"ce:given-name": "Boonlert", "ce:initials": "B.", "ce:surname": "Lumlertdacha", "ce:indexed-name": "Lumlertdacha B."}, "@seq": "7", "ce:initials": "B.", "@_fa": "true", "affiliation": {"@id": "60005262", "@href": "https://api.elsevier.com/content/affiliation/affiliation_id/60005262"}, "ce:surname": "Lumlertdacha", "@auid": "8874604400", "author-url": "https://api.elsevier.com/content/author/author_id/8874604400", "ce:indexed-name": "Lumlertdacha B."}, {"ce:given-name": "Veera", "preferred-name": {"ce:given-name": "Veera", "ce:initials": "V.", "ce:surname": "Tepsumethanon", "ce:indexed-name": "Tepsumethanon V."}, "@seq": "8", "ce:initials": "V.", "@_fa": "true", "affiliation": {"@id": "60005262", "@href": "https://api.elsevier.com/content/affiliation/affiliation_id/60005262"}, "ce:surname": "Tepsumethanon", "@auid": "6602544202", "author-url": "https://api.elsevier.com/content/author/author_id/6602544202", "ce:indexed-name": "Tepsumethanon V."}, {"ce:given-name": "Thiravat", "preferred-name": {"ce:given-name": "Thiravat", "ce:initials": "T.", "ce:surname": "Hemachudha", "ce:indexed-name": "Hemachudha T."}, "@seq": "9", "ce:initials": "T.", "@_fa": "true", "affiliation": [{"@id": "60091571", "@href": "https://api.elsevier.com/content/affiliation/affiliation_id/60091571"}, {"@id": "60028190", "@href": "https://api.elsevier.com/content/affiliation/affiliation_id/60028190"}], "ce:surname": "Hemachudha", "@auid": "7007163205", "author-url": "https://api.elsevier.com/content/author/author_id/7007163205", "ce:indexed-name": "Hemachudha T."}]}}}